odoo/addons/website_sale_coupon_selection_wizard/README.rst
odoo/addons/website_sale_coupon_selection_wizard/__init__.py
odoo/addons/website_sale_coupon_selection_wizard/__manifest__.py
odoo/addons/website_sale_coupon_selection_wizard/controllers/__init__.py
odoo/addons/website_sale_coupon_selection_wizard/controllers/coupon_page.py
odoo/addons/website_sale_coupon_selection_wizard/controllers/main.py
odoo/addons/website_sale_coupon_selection_wizard/controllers/promotion_wizard.py
odoo/addons/website_sale_coupon_selection_wizard/i18n/es.po
odoo/addons/website_sale_coupon_selection_wizard/i18n/website_sale_coupon_selection_wizard.pot
odoo/addons/website_sale_coupon_selection_wizard/readme/CONTRIBUTORS.rst
odoo/addons/website_sale_coupon_selection_wizard/readme/DESCRIPTION.rst
odoo/addons/website_sale_coupon_selection_wizard/readme/USAGE.rst
odoo/addons/website_sale_coupon_selection_wizard/static/description/icon.png
odoo/addons/website_sale_coupon_selection_wizard/static/description/index.html
odoo/addons/website_sale_coupon_selection_wizard/static/src/js/website_sale_coupon_selection_wizard.js
odoo/addons/website_sale_coupon_selection_wizard/static/src/scss/website_sale_coupon_selection.scss
odoo/addons/website_sale_coupon_selection_wizard/templates/assets.xml
odoo/addons/website_sale_coupon_selection_wizard/templates/promotion_templates.xml
odoo13_addon_website_sale_coupon_selection_wizard-13.0.1.0.1.dev5.dist-info/METADATA
odoo13_addon_website_sale_coupon_selection_wizard-13.0.1.0.1.dev5.dist-info/WHEEL
odoo13_addon_website_sale_coupon_selection_wizard-13.0.1.0.1.dev5.dist-info/top_level.txt
odoo13_addon_website_sale_coupon_selection_wizard-13.0.1.0.1.dev5.dist-info/RECORD
