Metadata-Version: 2.1
Name: odoo13-addon-website-sale-coupon-selection-wizard
Version: 13.0.1.0.1.dev5
Summary: Allows to apply and configure promotions directly from the website
Home-page: https://github.com/OCA/sale-promotion
Author: Tecnativa, Odoo Community Association (OCA)
Author-email: support@odoo-community.org
License: AGPL-3
Platform: UNKNOWN
Classifier: Programming Language :: Python
Classifier: Framework :: Odoo
Classifier: Framework :: Odoo :: 13.0
Classifier: License :: OSI Approved :: GNU Affero General Public License v3
Classifier: Development Status :: 4 - Beta
Requires-Python: >=3.5
Requires-Dist: odoo13-addon-sale-coupon-order-suggestion
Requires-Dist: odoo13-addon-sale-coupon-selection-wizard
Requires-Dist: odoo13-addon-website-sale-coupon-page
Requires-Dist: odoo <13.1dev,>=13.0a
